clumppling/__init__.py
clumppling/__main__.py
clumppling/alignAcrossK/__init__.py
clumppling/alignAcrossK/__main__.py
clumppling/alignAcrossK/utils.py
clumppling/alignWithinK/__init__.py
clumppling/alignWithinK/__main__.py
clumppling/alignWithinK/utils.py
clumppling/compModels/__init__.py
clumppling/compModels/__main__.py
clumppling/compModels/utils.py
clumppling/core.py
clumppling/detectMode/__init__.py
clumppling/detectMode/__main__.py
clumppling/detectMode/custom.py
clumppling/detectMode/utils.py
clumppling/files/default_colors.txt
clumppling/files/distruct_colors.txt
clumppling/log_config.py
clumppling/parseInput/__init__.py
clumppling/parseInput/__main__.py
clumppling/parseInput/utils.py
clumppling/plot.py
clumppling/utils.py
clumppling-2.0.6.dist-info/METADATA
clumppling-2.0.6.dist-info/WHEEL
clumppling-2.0.6.dist-info/entry_points.txt
clumppling-2.0.6.dist-info/RECORD
