Metadata-Version: 2.4
Name: clumppling
Version: 2.0.6
Summary: Clumppling: cluster matching and permutation program with integer linear programming
License: MIT
Keywords: alignment,clustering
Author: Xiran Liu
Author-email: xiranliu@stanford.edu
Requires-Python: >=3.9,<3.13
Classifier: License :: OSI Approved :: MIT License
Classifier: Programming Language :: Python :: 3
Classifier: Programming Language :: Python :: 3.9
Classifier: Programming Language :: Python :: 3.10
Classifier: Programming Language :: Python :: 3.11
Classifier: Programming Language :: Python :: 3.12
Requires-Dist: TracyWidom (==0.4.0)
Requires-Dist: cdlib (>=0.3,<0.4)
Requires-Dist: cvxpy[glpk] (==1.5)
Requires-Dist: matplotlib (>=3.7,<4.0)
Requires-Dist: networkx (>=3.0,<4.0)
Requires-Dist: numpy (>=1.24,<2.0)
Requires-Dist: scipy (>=1.10,<2.0)
